ahcp.cp37-win_amd64.pyd
mpml.py
sregex.cp37-win_amd64.pdb
sregex.cp37-win_amd64.pyd
mpml-1.0.1.dist-info/LICENSE
mpml-1.0.1.dist-info/METADATA
mpml-1.0.1.dist-info/WHEEL
mpml-1.0.1.dist-info/top_level.txt
mpml-1.0.1.dist-info/RECORD
