Metadata-Version: 2.1
Name: mpml
Version: 1.0.1
Summary: multi pattern match library
Home-page: UNKNOWN
Author: zhouzusheng
Author-email: zhouzusheng@aitek.ai
License: GNU LGPL
Platform: POSIX
Classifier: Development Status :: 4 - Beta
Classifier: Intended Audience :: Developers
Classifier: License :: OSI Approved :: GNU Library or Lesser General Public License (LGPL)
Classifier: Operating System :: POSIX
Classifier: Programming Language :: C
Classifier: Programming Language :: Python
Classifier: Topic :: Software Development :: Libraries :: Python Modules
Classifier: Topic :: Text Processing :: Indexing
Requires-Dist: setuptools
Requires-Dist: Cython
